activity/__init__.py
activity/admin.py
activity/apps.py
activity/middleware.py
activity/models.py
activity/tests.py
activity/views.py
activity/migrations/__init__.py
django_user_activity-0.0.1.dist-info/licenses/LICENSE
django_user_activity-0.0.1.dist-info/METADATA
django_user_activity-0.0.1.dist-info/WHEEL
django_user_activity-0.0.1.dist-info/top_level.txt
django_user_activity-0.0.1.dist-info/RECORD
