Metadata-Version: 2.4
Name: django-user-activity
Version: 0.0.1
Summary: A Django app for tracking user activity
Home-page: https://github.com/rkpust/django-user-activity
Author: Md. Rezaul Karim
Author-email: rezaul.cse.pust17@gamil.com
License: MIT
Classifier: Framework :: Django
Classifier: License :: OSI Approved :: MIT License
Classifier: Intended Audience :: Developers
Classifier: Programming Language :: Python
Classifier: Programming Language :: Python :: 3
Classifier: Operating System :: OS Independent
License-File: LICENSE
Requires-Dist: django
Dynamic: author
Dynamic: author-email
Dynamic: classifier
Dynamic: description
Dynamic: description-content-type
Dynamic: home-page
Dynamic: license
Dynamic: license-file
Dynamic: requires-dist
Dynamic: summary
